good_smell/__init__.py
good_smell/ast_smell.py
good_smell/flake8_ext.py
good_smell/lint_smell.py
good_smell/main.py
good_smell/smell_warning.py
good_smell/smells/__init__.py
good_smell/smells/filter.py
good_smell/smells/join_literal.py
good_smell/smells/nested_for.py
good_smell/smells/range_len_fix.py
good_smell/smells/yield_from.py
good_smell-0.18.dist-info/entry_points.txt
good_smell-0.18.dist-info/LICENSE
good_smell-0.18.dist-info/WHEEL
good_smell-0.18.dist-info/METADATA
good_smell-0.18.dist-info/RECORD
