Metadata-Version: 2.1
Name: good-smell
Version: 0.18
Summary: A linter/refactoring tool to make your code smell better!
Home-page: https://github.com/Tadaboody/good_smell
License: BSD-3-Clause
Author: Tomer Keren
Author-email: tomer.keren.dev@gmail.com
Requires-Python: >=3.6,<4.0
Classifier: Development Status :: 3 - Alpha
Classifier: Environment :: Console
Classifier: Framework :: Flake8
Classifier: License :: OSI Approved :: BSD License
Classifier: Operating System :: OS Independent
Classifier: Programming Language :: Python :: 3
Classifier: Programming Language :: Python :: 3.6
Classifier: Programming Language :: Python :: 3.7
Classifier: Programming Language :: Python :: 3.8
Classifier: Programming Language :: Python :: 3.9
Requires-Dist: astor
Requires-Dist: fire
Requires-Dist: flake8 (>=3,<4)
Project-URL: Repository, https://github.com/Tadaboody/good_smell
